{
  "creds": {
    "noiseKey": {
      "private": {
        "type": "Buffer",
        "data": "iBPn+cJTBIPgvDUkfXktcH0piaALK/AeSjP3kpJyMXU="
      },
      "public": {
        "type": "Buffer",
        "data": "opi9ibUah0WqfAUwdmQVdDaZ8loq31ITFEHNRPGwBzY="
      }
    },
    "signedIdentityKey": {
      "private": {
        "type": "Buffer",
        "data": "OOYTlOjXaQtLv6hm2o3gG8J0TLUG589rSR6aVrfzMkA="
      },
      "public": {
        "type": "Buffer",
        "data": "f50QdTbwnTPkuVeH4GvDR45v0YIdM9edS7zWydpm3X4="
      }
    },
    "signedPreKey": {
      "keyPair": {
        "private": {
          "type": "Buffer",
          "data": "UN0vPuDZTjiTsc8ufFSiicJAGppH5QdV3nVceiNV2Ek="
        },
        "public": {
          "type": "Buffer",
          "data": "0IPo1xjEdHwrzMsIhEEGzUutUSJ0l8gIchY3jxezcQQ="
        }
      },
      "signature": {
        "type": "Buffer",
        "data": "aEcvsvVVnDtahgMZd9w9VihRGZ4P6m7czvFZ2eA1nRauBcsohGGAusc9WG/OhMW1wd7IF9e1A7L9dVLI0aPBBQ=="
      },
      "keyId": 1
    },
    "registrationId": 129,
    "advSecretKey": "tGv2OSAVcBD6+5UDf9sj8XrIBjusWtP/x1l7mbzm9ng=",
    "processedHistoryMessages": [
      {
        "key": {
          "remoteJid": "447451215954@s.whatsapp.net",
          "fromMe": true,
          "id": "0418536D2769ABA34D2063EB3244DD24"
        },
        "messageTimestamp": 1661421310
      },
      {
        "key": {
          "remoteJid": "447451215954@s.whatsapp.net",
          "fromMe": true,
          "id": "6C63A991A3F5506BB6980894A01927F2"
        },
        "messageTimestamp": 1661421311
      }
    ],
    "nextPreKeyId": 61,
    "firstUnuploadedPreKeyId": 61,
    "accountSettings": {
      "unarchiveChats": false
    },
    "account": {
      "details": "CJa53pkCEPaNnZgGGAE=",
      "accountSignatureKey": "rebU4gJiisTFVc1Los3DsEJrKJUcB9ROpG3HODEtmiU=",
      "accountSignature": "P9HMm4xKP/pXoLc8Po/FzNIJpY01ZwFxeOXwH1aVOhqCbBwAj/t7/bj/adsjLbgDPqZxIK9y1v3DsTfOtJRyCA==",
      "deviceSignature": "oN1XPSLGYFgOb79hukOUc+59WGn6HsF2cYqxlAzvQy3LPpSPDFd9LHB7ckmish5o1867gjRzcNtjZUvIr87GBw=="
    },
    "me": {
      "id": "447451215954:1@s.whatsapp.net",
      "name": "🜋 | 𝐋𝐔𝐂𝐈𝐅𝐄𝐑 𓆩‎ま𓆪"
    },
    "signalIdentities": [
      {
        "identifier": {
          "name": "447451215954:1@s.whatsapp.net",
          "deviceId": 0
        },
        "identifierKey": {
          "type": "Buffer",
          "data": "Ba3m1OICYorExVXNS6LNw7BCayiVHAfUTqRtxzgxLZol"
        }
      }
    ],
    "platform": "android",
    "lastAccountSyncTimestamp": 1661421304,
    "myAppStateKeyId": "AAAAAA1u"
  },
  "keys": {
    "preKeys": {
      "1": {
        "private": {
          "type": "Buffer",
          "data": "+IUdBqqU9qcyDU94MB7txRmPqyZUk1ySb8vy2U9Jvk0="
        },
        "public": {
          "type": "Buffer",
          "data": "NVMOzuOZKRB77dg6u4O0NtKrYFd3ghL86iE6poESnEM="
        }
      },
      "2": {
        "private": {
          "type": "Buffer",
          "data": "2M8Tl5odaC/8lrza4vXgcEpOEIJHnDaVqSZZ0HiEtHc="
        },
        "public": {
          "type": "Buffer",
          "data": "HC8oBiAdE6w6MdOtdpiDSMUCKzCtHftpraMRgfNs8mU="
        }
      },
      "3": {
        "private": {
          "type": "Buffer",
          "data": "8IIsVHa9rRojP5HLMnpCYltk+aw6gRkBKbPndQ7lKHM="
        },
        "public": {
          "type": "Buffer",
          "data": "agh2d14bekIpAnpu3/gsrR4qZsirawl6pC2TmjxAVm8="
        }
      },
      "4": {
        "private": {
          "type": "Buffer",
          "data": "2EXRuRgZRXfE1qYu5ecKEv44gXa/aceMO+s5l7cLbVE="
        },
        "public": {
          "type": "Buffer",
          "data": "2eD84xaGehbnDxqvBxJLQuPq6asA7rBzcWs9w3SxiVg="
        }
      },
      "5": {
        "private": {
          "type": "Buffer",
          "data": "2FbjabmSdcgbJ9hUl9AsHgPFQmnJyKMm8drk0hjaCns="
        },
        "public": {
          "type": "Buffer",
          "data": "1NiTZRhG8CcglAjS23kg1RUC7ZOISwWUwx5wkl7t/FU="
        }
      },
      "6": {
        "private": {
          "type": "Buffer",
          "data": "8AvrtyJfO8a45K1IvKvcE/u3BmZacP2boaLCy6U22WA="
        },
        "public": {
          "type": "Buffer",
          "data": "fcPqlD2JOAkXxH+qhhwjD0Ky+lhtjL82U9mKdaJAMXY="
        }
      },
      "7": {
        "private": {
          "type": "Buffer",
          "data": "oGaJCafoxe0sMgCVhTGtT1BB8mJwJW9ipNkbYZqReUk="
        },
        "public": {
          "type": "Buffer",
          "data": "du+UkHndXUlp/oylAqbFtjlrfqLdM53LpvE2LCOhGV8="
        }
      },
      "8": {
        "private": {
          "type": "Buffer",
          "data": "EAlxtYuSOQoszpwHZjwuDW5FYGSpC1+8BZePcmylsGo="
        },
        "public": {
          "type": "Buffer",
          "data": "anMEDehlKUtv9drfWB7Chklo5L0h03t+81l/mUdDHTk="
        }
      },
      "9": {
        "private": {
          "type": "Buffer",
          "data": "qGfc3IStX4xfVXvKQ6Z12FSUa69B6y6Otx2/UVEvOl8="
        },
        "public": {
          "type": "Buffer",
          "data": "0ezjqpV4BsPa0HvGAuMnFem3dH5rMBL1Dt4FklfF0gE="
        }
      },
      "10": {
        "private": {
          "type": "Buffer",
          "data": "iIqrSUVMahcFz3TWSxztTN1rfoC2GzPBaT0UjdfZx0w="
        },
        "public": {
          "type": "Buffer",
          "data": "7b0IwCNZUbbKAzdLc9nO/A6Rfr1CvpTzFnnIT5yhuQc="
        }
      },
      "11": {
        "private": {
          "type": "Buffer",
          "data": "4A748yiJGerbNi0chUJNudIT0zYFk2jlHqyq5jelOFw="
        },
        "public": {
          "type": "Buffer",
          "data": "Qm+dgXUE99iDdBzENn+u4bedx2VwEVeDWtN6RulYumo="
        }
      },
      "12": {
        "private": {
          "type": "Buffer",
          "data": "6Nk5W0Oo2qQYGvirXlQPXdLHGcUdR6rQLJmXa7q+rkY="
        },
        "public": {
          "type": "Buffer",
          "data": "0PbgNc/5ay6XTDG6atueGzbaMC9ndzxoRv1CHOgHzzk="
        }
      },
      "13": {
        "private": {
          "type": "Buffer",
          "data": "iDTuBRMgFkJ6LOQb8qaLbT4+ahUbbQoM9v1ZI9lOgUw="
        },
        "public": {
          "type": "Buffer",
          "data": "P4yGDRLXlrMrvXzAYngMmTVlXvQ+d09CxgUTLHGDczc="
        }
      },
      "14": {
        "private": {
          "type": "Buffer",
          "data": "kBdTz7cSPl6NwsnfjpLMCx9j+Ommu7W44ZelIewgmn0="
        },
        "public": {
          "type": "Buffer",
          "data": "0qesTz698nbKrWFbPhkRoVLAst8hQK71PIvZjkIVXEI="
        }
      },
      "15": {
        "private": {
          "type": "Buffer",
          "data": "0JmTjEMAX+zx8NEXtJstm0ukY6KuRmFMR6buC0O5f04="
        },
        "public": {
          "type": "Buffer",
          "data": "N9xXvhqIJhkCYC3Boq7klixq78o46uTPiPlxggpqul0="
        }
      },
      "16": {
        "private": {
          "type": "Buffer",
          "data": "qGNZLl6O6xaCJJhpAv8EwOHmpTtJFxAEDfrr0P3xrXY="
        },
        "public": {
          "type": "Buffer",
          "data": "CVGR8AhW8be8IP7ghw/+OuFWk3ElNz9AjeZiPa8chmU="
        }
      },
      "17": {
        "private": {
          "type": "Buffer",
          "data": "COEfUjJTS4fodDq1j7JloKGu+/lZYFunKAGTNhdQW0U="
        },
        "public": {
          "type": "Buffer",
          "data": "qs9DXSfC+RmBwJTTh7JT3ShlgdX1V6khFEndu5xgFFs="
        }
      },
      "18": {
        "private": {
          "type": "Buffer",
          "data": "EPk2Tr/Gqm293TgpKXdEuY53coL5xjitpMCh82GPiVc="
        },
        "public": {
          "type": "Buffer",
          "data": "9dHOcVYGPNZeJcNolN4fiNzLRwNhvDVrbYctazHQkWk="
        }
      },
      "19": {
        "private": {
          "type": "Buffer",
          "data": "ILzRgb0QbRkIrsNrmyKtdIyAmyGkQA8H0RxT6dtun2o="
        },
        "public": {
          "type": "Buffer",
          "data": "TjnpORBEEUVCNJ9Odhh3cpefl99vd3/EvR42V4BCjSw="
        }
      },
      "20": {
        "private": {
          "type": "Buffer",
          "data": "SMbzlvwM96ff3Dsblrnlc1UBN31pdJtDBzb9xsorxnE="
        },
        "public": {
          "type": "Buffer",
          "data": "XFKGuxsKkswCuc3QCCZypZLnpgc/UfzKTj/JzjYLvX4="
        }
      },
      "21": {
        "private": {
          "type": "Buffer",
          "data": "qEMjE1jvTcs7tQMB5ZOuzQAvpXR7cnDfQOvI5v/89Uw="
        },
        "public": {
          "type": "Buffer",
          "data": "SaLLu/WymZDVCThbMuUMafEIguifIkG9HeQEZzVmBDs="
        }
      },
      "22": {
        "private": {
          "type": "Buffer",
          "data": "AMh0CLd5r74K1vVdyD6FMPKts/AZoz+ztyEGg/F7aHU="
        },
        "public": {
          "type": "Buffer",
          "data": "aSHFPPKqjo8jNYG7vR3rp0Hh8JO4h6jJVeKNWB0iOy0="
        }
      },
      "23": {
        "private": {
          "type": "Buffer",
          "data": "GLKy7LoG5DYU2A/z04N/YAFrg+7FqDcl0LEZMHe18F8="
        },
        "public": {
          "type": "Buffer",
          "data": "TkifnWipTH0G5SQBXyJt352bc9NASxmmaaizIEszURY="
        }
      },
      "24": {
        "private": {
          "type": "Buffer",
          "data": "sM9MyOpbggxEYIHZUp1enoMR1HdIczzEhBfoMY9/p0k="
        },
        "public": {
          "type": "Buffer",
          "data": "CjDooen4yw4+YQ4pG/WhKasfIsIU5uKMVabb10k7yCY="
        }
      },
      "25": {
        "private": {
          "type": "Buffer",
          "data": "yBwiwSIzmWbadFccT1ZAhlZKPKkoa2VpFFy6RcGqt3I="
        },
        "public": {
          "type": "Buffer",
          "data": "dRHLMpkTjKUGMf4mzQUAPOo98iRHq6MDa1TZBxAOnxM="
        }
      },
      "26": {
        "private": {
          "type": "Buffer",
          "data": "uG7hu6s/hQerAvXs33/DBDf64NoJmaTL05YpdN9UF3w="
        },
        "public": {
          "type": "Buffer",
          "data": "jqclPGZzAwf3VOY+lIwwZB7+8q5siiG6wWKHgsIrcEY="
        }
      },
      "27": {
        "private": {
          "type": "Buffer",
          "data": "yHF1Wa9sBWPmQMIGvUJ8RWr3UVo1K4O2YtnUmfblk3w="
        },
        "public": {
          "type": "Buffer",
          "data": "Cf0EYvMyI8Pq+B2ZB+xlGOIV6bxDuYVMjp2AyFgLYi0="
        }
      },
      "28": {
        "private": {
          "type": "Buffer",
          "data": "MJo2AHG4ozZnE8IdWTKGf8q5Y+wXMb+gYuK6eiU4kX4="
        },
        "public": {
          "type": "Buffer",
          "data": "aXI5LXPx4at2vZKuQXX0MPxxdSJmtVGjMGLsazqwqh4="
        }
      },
      "29": {
        "private": {
          "type": "Buffer",
          "data": "MLSwwBimDBz6piZ/fGobJ3s7u0ZkEX9KbpV9KX0IAks="
        },
        "public": {
          "type": "Buffer",
          "data": "7m1fsziVUeleFlS2VK/7p/XU0EtUOnQTJ5LJcGjVkxM="
        }
      },
      "30": {
        "private": {
          "type": "Buffer",
          "data": "SDcM7SSlhL37O3nKh0EHcku4muzyCRekyAGqrEBg8ko="
        },
        "public": {
          "type": "Buffer",
          "data": "Vr9lhtFus8jJ0YZmxTlhcPLjcuiUFcw5MNQByA1FQGM="
        }
      },
      "31": {
        "private": {
          "type": "Buffer",
          "data": "APXgeYGTRKSErnFl1Gdons3j9ZwzYDm1yq+GFOZwRVU="
        },
        "public": {
          "type": "Buffer",
          "data": "DpZnotsBjSfu4EO1RynQWSoj22Yb5KCaojvwQaxHrVE="
        }
      },
      "32": {
        "private": {
          "type": "Buffer",
          "data": "6IRj5YuvXpBpCtDQ9a4qkxziMlkmRvX7wFx8QdHkIHc="
        },
        "public": {
          "type": "Buffer",
          "data": "51AfkLVQbiIXKzJPCjrtpzJH1vZneBGZ2AStIbIzDHM="
        }
      },
      "33": {
        "private": {
          "type": "Buffer",
          "data": "UMwtDJVQ1KXsfBFDT+HbbB1SB9IhHSW5cH3NcT0LaHc="
        },
        "public": {
          "type": "Buffer",
          "data": "JyCtQG6qEMjy9umDnvOuxq/+rL8BZXPRY4TP/k/dt1g="
        }
      },
      "34": {
        "private": {
          "type": "Buffer",
          "data": "oFfsZuZyaufFCOVsJ/2mIb8FSZ2zhz5xnlOH5bo7pno="
        },
        "public": {
          "type": "Buffer",
          "data": "AMwf+RuQbAf+ifIZAoW/mfQb5BCUaCYSv45lU4bOFGQ="
        }
      },
      "35": {
        "private": {
          "type": "Buffer",
          "data": "mPBcDfZAVS52fPrbv+dZmf6gEKjA+RMDnl6T7elNtEE="
        },
        "public": {
          "type": "Buffer",
          "data": "zgMC7CLkSF3J8a+ekU9UlXbEuTBu9X59Q37MH8g+M3k="
        }
      },
      "36": {
        "private": {
          "type": "Buffer",
          "data": "aGfh+SM1r/NQnlkVXVYZm5yN5CfZX1e1fh4EQUnqdXQ="
        },
        "public": {
          "type": "Buffer",
          "data": "Rudk02JYV+PXx2IdU1Jdg+niiyo+EGlbddBzm57zlgA="
        }
      },
      "37": {
        "private": {
          "type": "Buffer",
          "data": "SCflAU8/5cbLB6JYtuqYNzqlHUmDdtreudd/ePED4l4="
        },
        "public": {
          "type": "Buffer",
          "data": "t+Qa6K3Ydos1Q6zP6ABqXe06xvmBb0m2eAHOCkc3/Tw="
        }
      },
      "38": {
        "private": {
          "type": "Buffer",
          "data": "eEY4g9FHMV74MW+qwYMNdjje4nTIAjXUP+eWBrW/oW4="
        },
        "public": {
          "type": "Buffer",
          "data": "/B8U/pz4PZKIrleOMOkUmF/eV0ERQJ/fORpYcMYCrSY="
        }
      },
      "39": {
        "private": {
          "type": "Buffer",
          "data": "QE6QsYVL7+K693+8wY3ygq2EGg/DCwDCRaJH0BrJEVg="
        },
        "public": {
          "type": "Buffer",
          "data": "dkrB/cnvof1/blmjLjGQpbAE7EfJQe6gUMsrraHZ+gY="
        }
      },
      "40": {
        "private": {
          "type": "Buffer",
          "data": "mG2qBQJBYsQAmFeOleka3QNPhzEOGmQ3ImDDKtuxBFA="
        },
        "public": {
          "type": "Buffer",
          "data": "YY8H5AFxAnXswzHzlOjyENKZ2H2/0jKuOz68iVGMyis="
        }
      },
      "41": {
        "private": {
          "type": "Buffer",
          "data": "kOxF2qfHqebg4EMijVeamdIDaCmL3Z1fiiYCSoOjmUg="
        },
        "public": {
          "type": "Buffer",
          "data": "JvQKgfTIs6pDwBAjUt6z4YwUuKtNKelwZObI9dqRsCI="
        }
      },
      "42": {
        "private": {
          "type": "Buffer",
          "data": "oP3JJ/eE8D2581NmKjcvYpCrctHpHrm1I/rBmdKfAmw="
        },
        "public": {
          "type": "Buffer",
          "data": "WVlcsjsQz4OAAUbGJSW8CzFd6rgXEY1yZiqSDX2NaV0="
        }
      },
      "43": {
        "private": {
          "type": "Buffer",
          "data": "AHx4GTr7yYpc5Pqmv+xzjiFdcwZ+VQwFCcAXt3515n4="
        },
        "public": {
          "type": "Buffer",
          "data": "/uYPI8oNMXDFjguB8DD6HVz02e0wSTtHo1kzVA5WPRk="
        }
      },
      "44": {
        "private": {
          "type": "Buffer",
          "data": "YHbg8CvQm6QX4ug4LRiV2oC5ooRQIHMaqdGxeh64qU0="
        },
        "public": {
          "type": "Buffer",
          "data": "eDe5Wgn1mbbJPwz5lR60WjnwdTyUd8lmAKU6aXFkZRk="
        }
      },
      "45": {
        "private": {
          "type": "Buffer",
          "data": "kGLxGrG18+qgSYZ8Kqzoa5G8DmN4ym5gUvA1jsOTxHA="
        },
        "public": {
          "type": "Buffer",
          "data": "3eGGpn25iaXMfz5vZsw/lse5ZmeFekEBN2duyvG9e04="
        }
      },
      "46": {
        "private": {
          "type": "Buffer",
          "data": "+ABQW6jHcmXubKHQaj2DGBGmZ5bgHZcNvLsz13rynko="
        },
        "public": {
          "type": "Buffer",
          "data": "dggvy32bfkZlHi2vIarrMMfx+rtFTDJ7CDTNgmwa0G8="
        }
      },
      "47": {
        "private": {
          "type": "Buffer",
          "data": "mHSOPkiuy7/LvXKwMcewdTv9Avc3Gy2iRAjiN3dkFXM="
        },
        "public": {
          "type": "Buffer",
          "data": "trmN6T2dUvOgtSnx4b+HmyaoWIvyQT8ZK99ksgQoiCo="
        }
      },
      "48": {
        "private": {
          "type": "Buffer",
          "data": "EBRdXS8JCEKF1NWmp/gZm4peX+G/aC5rTLe6MsG0404="
        },
        "public": {
          "type": "Buffer",
          "data": "Ui7aIGFUzym9SzbJlxeE2DcFxW2+iOAKDv+L4dl65wA="
        }
      },
      "49": {
        "private": {
          "type": "Buffer",
          "data": "ULaY8vBg5J5q0Je5oIxSTk5GmtPnHnS2v7Gopqtk7WY="
        },
        "public": {
          "type": "Buffer",
          "data": "sNOWO8Z9LiKgl1EH0xc+JhhNqayKEF0On3hG7JTsOEc="
        }
      },
      "50": {
        "private": {
          "type": "Buffer",
          "data": "CLYXmheVAqxkooyvS5cvJAb1vBkpxnq37IktM5OK+XQ="
        },
        "public": {
          "type": "Buffer",
          "data": "E6jrUsvYL+2Ts+yTPcTTyVblsfxnlmx5iWb4nFBobBQ="
        }
      },
      "51": {
        "private": {
          "type": "Buffer",
          "data": "EOM1pNAjQIfDa23ZxhLwzKks32QXrZ0gNxXQmd1ogGo="
        },
        "public": {
          "type": "Buffer",
          "data": "shVuV181uIteWXOrN2QiTU/YeMK5Al+h82Uh/LfO8ig="
        }
      },
      "52": {
        "private": {
          "type": "Buffer",
          "data": "wFXdZtx92AD+mE1SqQY2Tr0SAF9COfYh0EF30Fo563g="
        },
        "public": {
          "type": "Buffer",
          "data": "WNizRTyGlfbsG9PZ9qXLJV3nRPUltIG+4fbwBDBvJUc="
        }
      },
      "53": {
        "private": {
          "type": "Buffer",
          "data": "YLSWsF43d1j+iuZ5julO6L0eP4ey18KwI2aEvlkSB2s="
        },
        "public": {
          "type": "Buffer",
          "data": "2kK3Vd6FVJVP9lysp55ftk/4fhAvK1jKc4ViEtcrBCY="
        }
      },
      "54": {
        "private": {
          "type": "Buffer",
          "data": "+FVAkKQm5iVLUVV12wbe1VIwU39BAGFSNSMVIARu6W0="
        },
        "public": {
          "type": "Buffer",
          "data": "PchAt8KVeENKfx6N1iHa0NBWjyfIohK2b4eCCs+/LXg="
        }
      },
      "55": {
        "private": {
          "type": "Buffer",
          "data": "SKKkH1e5aBOW9T5ISRihntc9SA04YzbclfxF5Su8kUg="
        },
        "public": {
          "type": "Buffer",
          "data": "dQDUav7Em97Gna+ukeMmOfkGzT6ycUvHSG9R6ZqnZzE="
        }
      },
      "56": {
        "private": {
          "type": "Buffer",
          "data": "cGNz9g0mHiL/JjJG7WjUUpdcYBFMuZPDQax/b6Xme1s="
        },
        "public": {
          "type": "Buffer",
          "data": "LLI8v4BonE2KJ5RX652nzHOwOCFERVG4Lp7lVMLZaAQ="
        }
      },
      "57": {
        "private": {
          "type": "Buffer",
          "data": "GOV4suf9mlMX0I7frm6bChqWQs47ICNa6mdlhhvamUw="
        },
        "public": {
          "type": "Buffer",
          "data": "IILEZookjaVEYPluES7txy2jTvCFhA0NolWvnyoQB38="
        }
      },
      "58": {
        "private": {
          "type": "Buffer",
          "data": "uDKMkUa503aK0lv0IRJDvW3FXcBCQ1jtvJNZxOYXUXI="
        },
        "public": {
          "type": "Buffer",
          "data": "4kGlClVmlt4yodDURC4KmKISb9NdT4ukYAKZUXscJ34="
        }
      },
      "59": {
        "private": {
          "type": "Buffer",
          "data": "YNlNHy/KBKcQs/8SQz5X8mMjStEc75dBlauspsY2xF8="
        },
        "public": {
          "type": "Buffer",
          "data": "MWfl16r2zuUMENelZ3gxNrATUQ6Q9orTT5mvlhSFOE0="
        }
      },
      "60": {
        "private": {
          "type": "Buffer",
          "data": "oKOusI/25g/h+DBA1DVqzJOX0PIMadQ+2v4ly7f842I="
        },
        "public": {
          "type": "Buffer",
          "data": "tSdVd2CRIj+/KI4lhqU8mNvLxHSGU1l8lbVI9K4t50c="
        }
      }
    },
    "sessions": {
      "447451215954.0": {
        "_sessions": {
          "BRpluws8HnorLqxQiJf5TALEW+AVF0ktZHwhIBC6Fdwj": {
            "registrationId": 1035840437,
            "currentRatchet": {
              "ephemeralKeyPair": {
                "pubKey": "BWYuipl53OmvTi+DYOhFiNl55VDyMAmqEqqdF47oQCBR",
                "privKey": "kEIQI5VYjz/4d6vwhC/RZMu+Xe1OAvws1jZr5IoY/FY="
              },
              "lastRemoteEphemeralKey": "BYYwwv+/r7M6RChlofO9rgVdGky1Jxzppf6sYJtMEZQB",
              "previousCounter": 0,
              "rootKey": "YL3nupboLXiNf6uKaz/Fca3cnGIDvE7/0r/IMO2eD9c="
            },
            "indexInfo": {
              "baseKey": "BRpluws8HnorLqxQiJf5TALEW+AVF0ktZHwhIBC6Fdwj",
              "baseKeyType": 2,
              "closed": -1,
              "used": 1661421305858,
              "created": 1661421305858,
              "remoteIdentityKey": "Ba3m1OICYorExVXNS6LNw7BCayiVHAfUTqRtxzgxLZol"
            },
            "_chains": {
              "BYYwwv+/r7M6RChlofO9rgVdGky1Jxzppf6sYJtMEZQB": {
                "chainKey": {
                  "counter": 6,
                  "key": "ph6kYC5JT031g7Qh9zTiRKcx6AqgVQyu/OHBkfOdB78="
                },
                "chainType": 2,
                "messageKeys": {}
              },
              "BWYuipl53OmvTi+DYOhFiNl55VDyMAmqEqqdF47oQCBR": {
                "chainKey": {
                  "counter": 1,
                  "key": "Eqhh249daLT6vvj8qG8iFu2M0agjwA/bcwKdV9F1mvw="
                },
                "chainType": 1,
                "messageKeys": {}
              }
            }
          }
        },
        "version": "v1"
      }
    },
    "appStateSyncKeys": {
      "AAAAAA1u": {
        "keyData": "Iz2qQU8vblktGfGTmVI1tVXV+O+RfROoh+Vm9LEANzE=",
        "fingerprint": {
          "rawId": 590847126,
          "currentIndex": 1,
          "deviceIndexes": [
            0,
            1
          ]
        },
        "timestamp": "1661421305369"
      }
    },
    "appStateVersions": {
      "critical_block": {
        "version": 1,
        "hash": {
          "type": "Buffer",
          "data": "WIx/WZ75S5FA7vR/oTSXk6oPUkPMoYjbsac0l8jcNoHTOfs9dTzil6iP/+eLoPS0Y9o4BM6RNPcuOo+3cwwXdlRwhjFVtwHHkP722wNJBKi0HH3FT97v7oj7rVxRwCDNisRv+bh09tNPbdUzn5v9bFnAhtK26e6GvtTcslDKS6M="
        },
        "indexValueMap": {
          "I57uPjmKiallNmLjv0+hbWY63Q+89Zkuj2yhaGneTB8=": {
            "valueMac": {
              "type": "Buffer",
              "data": "WaOxap7KZvFyv0flHS5kW8k/UiRK/Q3nOjYK8+HsFWc="
            }
          },
          "NE5AK8YYZuArRyNjUHVHnQgNaUqKncBWZctcZ/A4gjw=": {
            "valueMac": {
              "type": "Buffer",
              "data": "6vi2/5P6WHz59GNrn9r4K8f8C47c9noWJcsMQ8EQq6Y="
            }
          }
        }
      },
      "regular": {
        "version": 1,
        "hash": {
          "type": "Buffer",
          "data": "6wnvxQT9MYynbEKzfksB7RQrGQ5fcMZ35unsXnPKAUQdRXt11V6vlHT68fjxT4eojJMYouDYRf3omDuhEd0tqep3yTUlILZIqwyd6tbd1kHwqC/ltKeCSHzttKxml1+gep5hO05vD1RFoNjItc/6Aq5mBuEuYRY2uKs6EXBaroQ="
        },
        "indexValueMap": {
          "5bSp7Mx2RB2lTgT1284JRN6nadvzHPxJwwxC/uO411I=": {
            "valueMac": {
              "type": "Buffer",
              "data": "UXuC5iLF2Ty//D4W4NpOO6TF7tbyCXIj2cu99kCGGy8="
            }
          }
        }
      }
    }
  }
}